aipromptlite/__init__.py
aipromptlite/claude/CLAUDE_SYS_PROMPT.md
aipromptlite/claude/PREVIEW_SYS_PROMPT.md
aipromptlite/claude/__init__.py
aipromptlite/code/CODE_EXPLANATION_CLAUDE_PROMPT.md
aipromptlite/code/CODE_GENERATION_PROMPT.md
aipromptlite/code/__init__.py
aipromptlite/content_writer/EXPERT_TECHNICAL_WRITER.md
aipromptlite/content_writer/__init__.py
aipromptlite/education/TECHNICAL_EXPLANATIONS.md
aipromptlite/education/__init__.py
aipromptlite/language/PYTHON_CODER_PROMPT.md
aipromptlite/language/__init__.py
aipromptlite/personas/AI_TECH_LEAD_PROMPT.md
aipromptlite/personas/BRAINSTROM_BUDDY_PROMPT.md
aipromptlite/personas/__init__.py
aipromptlite/reasoning/PREDICTIVE_QUESTION_REASONING_PROMPT.md
aipromptlite/reasoning/__init__.py
aipromptlite-0.1.18.dist-info/METADATA
aipromptlite-0.1.18.dist-info/WHEEL
aipromptlite-0.1.18.dist-info/RECORD
